pydggrid.cp36-win32.pyd
pydggrid-0.0.16.data/data/LIBEAY32.dll
pydggrid-0.0.16.data/data/SSLEAY32.dll
pydggrid-0.0.16.data/data/expat.dll
pydggrid-0.0.16.data/data/gdal204.dll
pydggrid-0.0.16.data/data/geos.dll
pydggrid-0.0.16.data/data/geos_c.dll
pydggrid-0.0.16.data/data/libcharset.dll
pydggrid-0.0.16.data/data/libcurl.dll
pydggrid-0.0.16.data/data/libiconv.dll
pydggrid-0.0.16.data/data/libpng16.dll
pydggrid-0.0.16.data/data/libpq.dll
pydggrid-0.0.16.data/data/libxml2.dll
pydggrid-0.0.16.data/data/lzma.dll
pydggrid-0.0.16.data/data/openjp2.dll
pydggrid-0.0.16.data/data/shp.dll
pydggrid-0.0.16.data/data/sqlite3.dll
pydggrid-0.0.16.data/data/webp.dll
pydggrid-0.0.16.data/data/zlib1.dll
pydggrid-0.0.16.dist-info/LICENSE
pydggrid-0.0.16.dist-info/METADATA
pydggrid-0.0.16.dist-info/WHEEL
pydggrid-0.0.16.dist-info/top_level.txt
pydggrid-0.0.16.dist-info/RECORD
